torchx/__init__.py
torchx/notebook.py
torchx/version.py
torchx/version.txt
torchx/apps/__init__.py
torchx/apps/serve/__init__.py
torchx/apps/serve/serve.py
torchx/apps/utils/__init__.py
torchx/apps/utils/booth_main.py
torchx/apps/utils/copy_main.py
torchx/apps/utils/process_monitor.py
torchx/cli/__init__.py
torchx/cli/argparse_util.py
torchx/cli/cmd_base.py
torchx/cli/cmd_cancel.py
torchx/cli/cmd_configure.py
torchx/cli/cmd_delete.py
torchx/cli/cmd_describe.py
torchx/cli/cmd_list.py
torchx/cli/cmd_log.py
torchx/cli/cmd_run.py
torchx/cli/cmd_runopts.py
torchx/cli/cmd_status.py
torchx/cli/cmd_tracker.py
torchx/cli/colors.py
torchx/cli/main.py
torchx/components/__init__.py
torchx/components/component_test_base.py
torchx/components/dist.py
torchx/components/interpret.py
torchx/components/metrics.py
torchx/components/serve.py
torchx/components/structured_arg.py
torchx/components/train.py
torchx/components/utils.py
torchx/components/integration_tests/__init__.py
torchx/components/integration_tests/component_provider.py
torchx/components/integration_tests/integ_tests.py
torchx/distributed/__init__.py
torchx/examples/__init__.py
torchx/examples/torchx_out_of_sync_training.py
torchx/examples/apps/__init__.py
torchx/examples/apps/datapreproc/__init__.py
torchx/examples/apps/datapreproc/datapreproc.py
torchx/examples/apps/lightning/__init__.py
torchx/examples/apps/lightning/data.py
torchx/examples/apps/lightning/interpret.py
torchx/examples/apps/lightning/model.py
torchx/examples/apps/lightning/profiler.py
torchx/examples/apps/lightning/train.py
torchx/pipelines/__init__.py
torchx/runner/__init__.py
torchx/runner/api.py
torchx/runner/config.py
torchx/runner/events/__init__.py
torchx/runner/events/api.py
torchx/runner/events/handlers.py
torchx/runtime/__init__.py
torchx/runtime/tracking/__init__.py
torchx/runtime/tracking/api.py
torchx/schedulers/__init__.py
torchx/schedulers/api.py
torchx/schedulers/aws_batch_scheduler.py
torchx/schedulers/aws_sagemaker_scheduler.py
torchx_nightly-2026.1.26.dist-info/licenses/LICENSE
torchx_nightly-2026.1.26.dist-info/METADATA
torchx_nightly-2026.1.26.dist-info/WHEEL
torchx_nightly-2026.1.26.dist-info/entry_points.txt
torchx_nightly-2026.1.26.dist-info/top_level.txt
torchx_nightly-2026.1.26.dist-info/RECORD
