Metadata-Version: 2.4
Name: torchx-nightly
Version: 2026.1.26
Summary: TorchX SDK and Components
Home-page: https://github.com/meta-pytorch/torchx
Author: TorchX Devs
Author-email: torchx@fb.com
License: BSD-3
Keywords: pytorch,machine learning
Classifier: Development Status :: 4 - Beta
Classifier: Intended Audience :: Developers
Classifier: Intended Audience :: Science/Research
Classifier: License :: OSI Approved :: BSD License
Classifier: Programming Language :: Python :: 3
Classifier: Programming Language :: Python :: 3.8
Classifier: Topic :: Scientific/Engineering :: Artificial Intelligence
Requires-Python: >=3.7
License-File: LICENSE
Requires-Dist: docstring-parser>=0.8.1
Requires-Dist: pyyaml
Requires-Dist: docker
Requires-Dist: filelock
Requires-Dist: fsspec>=2023.10.0
Requires-Dist: tabulate
Requires-Dist: typing-extensions
Provides-Extra: aws-batch
Requires-Dist: boto3; extra == "aws-batch"
Provides-Extra: kubernetes
Requires-Dist: kubernetes>=11; extra == "kubernetes"
Provides-Extra: dev
Requires-Dist: aiobotocore==2.20.0; extra == "dev"
Requires-Dist: ax-platform[mysql]==0.2.3; extra == "dev"
Requires-Dist: boto3==1.36.0; extra == "dev"
Requires-Dist: captum>=0.4.0; extra == "dev"
Requires-Dist: docker; extra == "dev"
Requires-Dist: kubernetes==25.3.0; extra == "dev"
Requires-Dist: flake8==3.9.0; extra == "dev"
Requires-Dist: fsspec==2024.3.1; extra == "dev"
Requires-Dist: s3fs==2024.3.1; extra == "dev"
Requires-Dist: hydra-core; extra == "dev"
Requires-Dist: ipython; extra == "dev"
Requires-Dist: mlflow-skinny; extra == "dev"
Requires-Dist: moto~=5.0.8; extra == "dev"
Requires-Dist: pyre-extensions; extra == "dev"
Requires-Dist: pyre-check; extra == "dev"
Requires-Dist: pytest; extra == "dev"
Requires-Dist: pytest-cov; extra == "dev"
Requires-Dist: pytorch-lightning==2.5.0; extra == "dev"
Requires-Dist: tensorboard==2.14.0; extra == "dev"
Requires-Dist: sagemaker==2.237.3; extra == "dev"
Requires-Dist: torch-model-archiver>=0.4.2; extra == "dev"
Requires-Dist: torch; extra == "dev"
Requires-Dist: torchmetrics==1.6.3; extra == "dev"
Requires-Dist: torchserve>=0.10.0; extra == "dev"
Requires-Dist: torchtext; extra == "dev"
Requires-Dist: torchvision; extra == "dev"
Requires-Dist: typing-extensions; extra == "dev"
Requires-Dist: ts==0.5.1; extra == "dev"
Requires-Dist: wheel; extra == "dev"
Requires-Dist: lintrunner; extra == "dev"
Requires-Dist: lintrunner-adapters; extra == "dev"
Dynamic: author
Dynamic: author-email
Dynamic: classifier
Dynamic: description
Dynamic: description-content-type
Dynamic: home-page
Dynamic: keywords
Dynamic: license
Dynamic: license-file
Dynamic: provides-extra
Dynamic: requires-dist
Dynamic: requires-python
Dynamic: summary
